estats_client/__init__.py
estats_client/client.py
estats_client/py.typed
estats_client/models/catalog.py
estats_client/models/result.py
estats_client/models/result_get_catalog.py
estats_client-0.1.3.dist-info/METADATA
estats_client-0.1.3.dist-info/WHEEL
estats_client-0.1.3.dist-info/RECORD
