Metadata-Version: 2.4
Name: estats-client
Version: 0.1.3
Summary: A Python client for the e-Stat API.
Project-URL: Homepage, https://github.com/example/estats-client
Project-URL: Repository, https://github.com/example/estats-client
Author-email: EFEXP <maeda_kentaro@cyberagent.co.jp>
License: MIT License
Keywords: api,client,estat,statistics,政府統計
Classifier: Development Status :: 3 - Alpha
Classifier: Intended Audience :: Developers
Classifier: License :: OSI Approved :: MIT License
Classifier: Programming Language :: Python :: 3
Classifier: Programming Language :: Python :: 3.8
Classifier: Programming Language :: Python :: 3.9
Classifier: Programming Language :: Python :: 3.10
Classifier: Programming Language :: Python :: 3.11
Classifier: Programming Language :: Python :: 3.12
Classifier: Topic :: Internet
Classifier: Topic :: Software Development :: Libraries :: Python Modules
Requires-Python: >=3.8
Requires-Dist: pydantic>=2.7.4
Requires-Dist: requests>=2.32.3
Requires-Dist: tenacity>=9.1.2
